README.md
setup.py
mintel_doppelganger/__init__.py
mintel_doppelganger.egg-info/PKG-INFO
mintel_doppelganger.egg-info/SOURCES.txt
mintel_doppelganger.egg-info/dependency_links.txt
mintel_doppelganger.egg-info/top_level.txt