Metadata-Version: 1.2
Name: mintel-doppelganger
Version: 1.0.3
Summary: Doppelganger?
Home-page: https://github.com/pypa/sampleproject
Author: Kevin Soules
Author-email: inceax64@gmail.com
License: UNKNOWN
Platform: UNKNOWN
Classifier: Programming Language :: Python :: 3
Classifier: Operating System :: OS Independent
Requires-Python: >=3.6
